autoterminal/__init__.py
autoterminal/main.py
autoterminal/config/__init__.py
autoterminal/config/loader.py
autoterminal/config/manager.py
autoterminal/history/__init__.py
autoterminal/history/history.py
autoterminal/llm/__init__.py
autoterminal/llm/client.py
autoterminal/utils/__init__.py
autoterminal/utils/helpers.py
autoterminal/utils/logger.py
autoterminal-1.0.2.dist-info/licenses/LICENSE
autoterminal-1.0.2.dist-info/METADATA
autoterminal-1.0.2.dist-info/WHEEL
autoterminal-1.0.2.dist-info/entry_points.txt
autoterminal-1.0.2.dist-info/top_level.txt
autoterminal-1.0.2.dist-info/RECORD
