Metadata-Version: 2.4
Name: autoterminal
Version: 1.0.2
Summary: 智能终端工具，基于LLM将自然语言转换为终端命令(create by claude 4 sonnet)
Author-email: wds2dxh <wdsnpshy@163.com>
License: MIT
Project-URL: Homepage, https://github.com/wds-dxh/AutoTerminal.git
Project-URL: Repository, https://github.com/wds-dxh/AutoTerminal.git
Project-URL: Issues, https://github.com/wds-dxh/AutoTerminal/issues
Keywords: terminal,ai,llm,command-line,automation,autoterminal
Classifier: Development Status :: 6 - Mature
Classifier: Intended Audience :: Developers
Classifier: Intended Audience :: System Administrators
Classifier: License :: OSI Approved :: MIT License
Classifier: Operating System :: OS Independent
Classifier: Programming Language :: Python :: 3
Classifier: Programming Language :: Python :: 3.10
Classifier: Programming Language :: Python :: 3.11
Classifier: Programming Language :: Python :: 3.12
Classifier: Topic :: System :: Systems Administration
Classifier: Topic :: Utilities
Requires-Python: >=3.10
License-File: LICENSE
Requires-Dist: openai>=1.0.0
Requires-Dist: loguru>=0.7.0
Dynamic: license-file
